autotui/__init__.py
autotui/edit.py
autotui/exceptions.py
autotui/fileio.py
autotui/namedtuple_prompt.py
autotui/options.py
autotui/pick.py
autotui/prompts.py
autotui/py.typed
autotui/serialize.py
autotui/shortcuts.py
autotui/typehelpers.py
autotui/warn.py
autotui-0.4.8.dist-info/licenses/LICENSE
autotui-0.4.8.dist-info/METADATA
autotui-0.4.8.dist-info/WHEEL
autotui-0.4.8.dist-info/top_level.txt
autotui-0.4.8.dist-info/RECORD
