Metadata-Version: 2.4
Name: autotui
Version: 0.4.8
Summary: "quickly create UIs to interactively prompt, validate, and persist python objects to disk (JSON/YAML) and back using type hints"
Author: purarue
License-Expression: MIT
Project-URL: Homepage, https://github.com/purarue/autotui
Keywords: data,prompt,namedtuple
Classifier: Programming Language :: Python
Classifier: Programming Language :: Python :: 3
Classifier: Programming Language :: Python :: 3 :: Only
Classifier: Programming Language :: Python :: 3.10
Classifier: Programming Language :: Python :: 3.11
Classifier: Programming Language :: Python :: 3.12
Classifier: Programming Language :: Python :: 3.13
Requires-Python: >=3.10
License-File: LICENSE
Requires-Dist: PyYAML>=6.0
Requires-Dist: click>=8.0
Requires-Dist: dateparser>=1.1.0
Requires-Dist: prompt-toolkit>=3.0
Provides-Extra: edit
Requires-Dist: click; extra == "edit"
Provides-Extra: json
Requires-Dist: orjson; extra == "json"
Provides-Extra: optional
Requires-Dist: click; extra == "optional"
Requires-Dist: orjson; extra == "optional"
Requires-Dist: pyfzf-iter; extra == "optional"
Provides-Extra: pick
Requires-Dist: pyfzf-iter; extra == "pick"
Provides-Extra: testing
Requires-Dist: flake8; extra == "testing"
Requires-Dist: mypy; extra == "testing"
Requires-Dist: pytest; extra == "testing"
Dynamic: license-file
